tap_facebook/__init__.py
tap_facebook/insights_experiment.py
tap_facebook/process_output.py
tap_facebook/schemas/adcreative.json
tap_facebook/schemas/ads.json
tap_facebook/schemas/ads_insights.json
tap_facebook/schemas/ads_insights_age_and_gender.json
tap_facebook/schemas/ads_insights_country.json
tap_facebook/schemas/ads_insights_dma.json
tap_facebook/schemas/ads_insights_platform_and_device.json
tap_facebook/schemas/ads_insights_region.json
tap_facebook/schemas/adsets.json
tap_facebook/schemas/campaigns.json
tap_facebook/schemas/shared/ads_action_stats.json
tap_facebook/schemas/shared/ads_histogram_stats.json
tap_facebook/schemas/shared/ads_image_crops.json
tap_facebook/schemas/shared/geo_locations.json
tap_facebook/schemas/shared/targeting.json
scnt_tap_facebook-1.8.5.dist-info/LICENSE
scnt_tap_facebook-1.8.5.dist-info/METADATA
scnt_tap_facebook-1.8.5.dist-info/WHEEL
scnt_tap_facebook-1.8.5.dist-info/entry_points.txt
scnt_tap_facebook-1.8.5.dist-info/top_level.txt
scnt_tap_facebook-1.8.5.dist-info/RECORD
